jqueryquerybuilder-0.1.0.dist-info/DESCRIPTION.rst
jqueryquerybuilder-0.1.0.dist-info/METADATA
jqueryquerybuilder-0.1.0.dist-info/RECORD
jqueryquerybuilder-0.1.0.dist-info/WHEEL
jqueryquerybuilder-0.1.0.dist-info/metadata.json
jqueryquerybuilder-0.1.0.dist-info/top_level.txt
querybuilder/__init__.py
querybuilder/constants.py
querybuilder/core.py
querybuilder/filters.py
querybuilder/rules.py
