Metadata-Version: 2.0
Name: jqueryquerybuilder
Version: 0.1.0
Summary: Generator and Parser for the jQuery Query Builder library.
Home-page: https://github.com/NorthIsUp/querybuilder
Author: Adam Hitchcock
Author-email: adam@northisup.com
License: MIT license
Keywords: querybuilder
Platform: UNKNOWN
Classifier: Development Status :: 2 - Pre-Alpha
Classifier: Intended Audience :: Developers
Classifier: License :: OSI Approved :: MIT License
Classifier: Natural Language :: English
Classifier: Programming Language :: Python :: 2
Classifier: Programming Language :: Python :: 2.6
Classifier: Programming Language :: Python :: 2.7
Classifier: Programming Language :: Python :: 3
Classifier: Programming Language :: Python :: 3.3
Classifier: Programming Language :: Python :: 3.4
Classifier: Programming Language :: Python :: 3.5
Requires-Dist: cached-property
Requires-Dist: enum34
Requires-Dist: six
